pytpt/__init__.py
pytpt/finite.py
pytpt/periodic.py
pytpt/stationary.py
pytpt/validation.py
pytpt-0.0.3.dist-info/METADATA
pytpt-0.0.3.dist-info/WHEEL
pytpt-0.0.3.dist-info/license.txt
pytpt-0.0.3.dist-info/top_level.txt
pytpt-0.0.3.dist-info/RECORD
