Metadata-Version: 2.1
Name: pytpt
Version: 0.0.3
Summary: Implementation of Transition Path Theory for stationary, periodically varying, and finite-time Markov chains.
Home-page: https://github.com/LuzieH/pytpt
Author: Luzie Helfmann and Enric Ribera Borrell
Author-email: luzie.helfmann@fu-berlin.de
License: UNKNOWN
Platform: UNKNOWN
Requires-Dist: numpy
Requires-Dist: scipy
